Metadata-Version: 2.1
Name: evalml
Version: 0.84.0
Summary: an AutoML library that builds, optimizes, and evaluates machine learning pipelines using domain-specific objective functions
Author-email: "Alteryx, Inc." <open_source_support@alteryx.com>
Maintainer-email: "Alteryx, Inc." <open_source_support@alteryx.com>
License: BSD 3-Clause License
Project-URL: Documentation, https://evalml.alteryx.com
Project-URL: Source Code, https://github.com/alteryx/evalml/
Project-URL: Changes, https://evalml.alteryx.com/en/latest/release_notes.html
Project-URL: Issue Tracker, https://github.com/alteryx/evalml/issues
Project-URL: Twitter, https://twitter.com/alteryxoss
Project-URL: Chat, https://join.slack.com/t/alteryx-oss/shared_invite/zt-182tyvuxv-NzIn6eiCEf8TBziuKp0bNA
Keywords: data science,machine learning,optimization,automl
Classifier: Development Status :: 4 - Beta
Classifier: Intended Audience :: Science/Research
Classifier: Intended Audience :: Developers
Classifier: Topic :: Software Development
Classifier: Topic :: Scientific/Engineering
Classifier: Programming Language :: Python
Classifier: Programming Language :: Python :: 3
Classifier: Programming Language :: Python :: 3.9
Classifier: Programming Language :: Python :: 3.10
Classifier: Programming Language :: Python :: 3.11
Classifier: Operating System :: Microsoft :: Windows
Classifier: Operating System :: POSIX
Classifier: Operating System :: Unix
Classifier: Operating System :: MacOS
Requires-Python: <4,>=3.9
License-File: LICENSE
Requires-Dist: numpy >=1.22.0
Requires-Dist: pandas <2.1.0,>=1.5.0
Requires-Dist: scipy >=1.5.0
Requires-Dist: scikit-learn >=1.3.2
Requires-Dist: scikit-optimize >=0.9.0
Requires-Dist: pyzmq >=20.0.0
Requires-Dist: colorama >=0.4.4
Requires-Dist: cloudpickle >=1.5.0
Requires-Dist: click >=8.0.0
Requires-Dist: shap >=0.45.0
Requires-Dist: statsmodels >=0.12.2
Requires-Dist: texttable >=1.6.2
Requires-Dist: woodwork[dask] >=0.22.0
Requires-Dist: dask !=2022.10.1,>=2022.2.0
Requires-Dist: distributed !=2022.10.1,>=2022.2.0
Requires-Dist: featuretools[dask] >=1.16.0
Requires-Dist: nlp-primitives >=2.9.0
Requires-Dist: networkx >=2.7
Requires-Dist: plotly >=5.0.0
Requires-Dist: kaleido >=0.2.0
Requires-Dist: ipywidgets >=7.5
Requires-Dist: xgboost >=1.7.0.post0
Requires-Dist: catboost >=1.1.1
Requires-Dist: lightgbm >=4.0.0
Requires-Dist: matplotlib >=3.3.3
Requires-Dist: seaborn >=0.11.1
Requires-Dist: category-encoders <=2.5.1.post0,>=2.2.2
Requires-Dist: imbalanced-learn >=0.11.0
Requires-Dist: pmdarima >=1.8.5
Requires-Dist: sktime <0.29.0,>=0.21.0
Requires-Dist: lime >=0.2.0.1
Requires-Dist: tomli >=2.0.1
Requires-Dist: packaging >=23.0
Requires-Dist: black[jupyter] >=22.3.0
Requires-Dist: holidays >=0.13
Requires-Dist: graphviz >=0.13 ; platform_system != "Windows"
Provides-Extra: complete
Requires-Dist: evalml[prophet,updater] ; extra == 'complete'
Provides-Extra: dev
Requires-Dist: ruff >=0.0.228 ; extra == 'dev'
Requires-Dist: darglint >=1.8.0 ; extra == 'dev'
Requires-Dist: pre-commit >=2.20.0 ; extra == 'dev'
Requires-Dist: evalml[docs,test] ; extra == 'dev'
Provides-Extra: docs
Requires-Dist: docutils <0.17,>=0.15.2 ; extra == 'docs'
Requires-Dist: pydata-sphinx-theme >=0.3.1 ; extra == 'docs'
Requires-Dist: astroid <=2.6.6 ; extra == 'docs'
Requires-Dist: Sphinx >=5.0.0 ; extra == 'docs'
Requires-Dist: nbconvert >=6.5.0 ; extra == 'docs'
Requires-Dist: nbsphinx <0.9.0,>=0.8.5 ; extra == 'docs'
Requires-Dist: sphinx-autoapi ; extra == 'docs'
Requires-Dist: sphinx-inline-tabs >=2022.1.2b11 ; extra == 'docs'
Requires-Dist: sphinx-copybutton >=0.4.0 ; extra == 'docs'
Requires-Dist: myst-parser >=0.18.0 ; extra == 'docs'
Provides-Extra: prophet
Requires-Dist: prophet >=1.1.2 ; extra == 'prophet'
Provides-Extra: test
Requires-Dist: pytest >=7.1.2 ; extra == 'test'
Requires-Dist: pytest-xdist >=2.1.0 ; extra == 'test'
Requires-Dist: pytest-timeout >=1.4.2 ; extra == 'test'
Requires-Dist: pytest-cov >=2.10.1 ; extra == 'test'
Requires-Dist: nbval >=0.9.3 ; extra == 'test'
Requires-Dist: IPython >=8.10.0 ; extra == 'test'
Requires-Dist: PyYAML >=6.0.1 ; extra == 'test'
Requires-Dist: coverage[toml] >=6.4 ; extra == 'test'
Provides-Extra: updater
Requires-Dist: alteryx-open-src-update-checker >=2.1.0 ; extra == 'updater'
